{
    "verslagen": {
        "delete": {
            "sql": "delete from VERSLAGEN where id in (?)",
            "values": [
                [
                    567
                ],
                [
                    568
                ],
                [
                    574
                ],
                [
                    572
                ],
                [
                    575
                ],
                [
                    576
                ],
                [
                    578
                ],
                [
                    592
                ],
                [
                    590
                ],
                [
                    570
                ],
                [
                    588
                ],
                [
                    582
                ],
                [
                    584
                ],
                [
                    585
                ]
            ],
            "concatenate": true
        }
    },
    "verslagen_files": {
        "delete": {
            "sql": "delete from VERSLAGEN_FILES where verslag_id=? and file_id=?",
            "values": [
                [
                    567,
                    4914
                ],
                [
                    568,
                    4915
                ],
                [
                    574,
                    4913
                ],
                [
                    572,
                    4910
                ],
                [
                    575,
                    4899
                ],
                [
                    576,
                    4912
                ],
                [
                    578,
                    4911
                ],
                [
                    592,
                    4894
                ],
                [
                    590,
                    4895
                ],
                [
                    570,
                    4901
                ],
                [
                    588,
                    4898
                ],
                [
                    582,
                    4900
                ],
                [
                    584,
                    4896
                ],
                [
                    585,
                    4897
                ]
            ],
            "concatenate": false
        },
        "insert": {
            "sql": "insert into VERSLAGEN_FILES (verslag_id,file_id) values(?,?)",
            "values": [
                [
                    566,
                    4914
                ],
                [
                    566,
                    4915
                ],
                [
                    573,
                    4913
                ],
                [
                    571,
                    4910
                ],
                [
                    95,
                    4899
                ],
                [
                    96,
                    4912
                ],
                [
                    577,
                    4911
                ],
                [
                    591,
                    4894
                ],
                [
                    589,
                    4895
                ],
                [
                    569,
                    4901
                ],
                [
                    587,
                    4898
                ],
                [
                    581,
                    4900
                ],
                [
                    583,
                    4896
                ],
                [
                    583,
                    4897
                ]
            ],
            "concatenate": true
        }
    }
}